graphamole/__init__.py
graphamole/__main__.py
graphamole/data.py
graphamole/dataloader.py
graphamole/lightning.py
graphamole/architecture/__init__.py
graphamole/architecture/decoder.py
graphamole/architecture/encoder.py
graphamole/architecture/graph_masking.py
graphamole/featurizers/__init__.py
graphamole/featurizers/abc.py
graphamole/featurizers/atom.py
graphamole/featurizers/bond.py
graphamole/featurizers/collection.py
graphamole-0.1.0.dist-info/METADATA
graphamole-0.1.0.dist-info/WHEEL
graphamole-0.1.0.dist-info/entry_points.txt
graphamole-0.1.0.dist-info/top_level.txt
graphamole-0.1.0.dist-info/RECORD
